app/__init__.py
app/config.py
app/rapid_email.py
test_rapid_email-1.0.dist-info/METADATA
test_rapid_email-1.0.dist-info/WHEEL
test_rapid_email-1.0.dist-info/top_level.txt
test_rapid_email-1.0.dist-info/RECORD
