Metadata-Version: 2.1
Name: test-rapid-email
Version: 1.0
Summary: Sending email notification.
Author: Abhishek Negi
